{
  "factoryPath": "filters.allpass",
  "nodes": [
    { "id": "in", "label": "Audio In", "type": "input", "importance": 1.0, "description": "Input audio signal" },
    { "id": "allpass", "label": "Phaser Allpass Chain", "type": "process", "importance": 1.0, "description": "6-stage cascaded first-order allpass with feedback, mixed with dry input" },
    { "id": "freq", "label": "Frequency", "type": "parameter", "importance": 1.0, "description": "Center frequency for allpass delay (20-20000 Hz), smoothed" },
    { "id": "q", "label": "Q", "type": "parameter", "importance": 1.0, "description": "Feedback amount (0.3-9.9 mapped to 0.0-0.99)" },
    { "id": "gain", "label": "Gain", "type": "parameter", "importance": 0.2, "description": "Ignored" },
    { "id": "mode", "label": "Mode", "type": "parameter", "importance": 0.2, "description": "Single mode: AllPass" },
    { "id": "smoothing", "label": "Smoothing", "type": "parameter", "importance": 0.5, "description": "Parameter interpolation time in seconds" },
    { "id": "enabled", "label": "Enabled", "type": "parameter", "importance": 0.5, "description": "Hard bypass toggle" },
    { "id": "coeffs", "label": "Filter Display", "type": "external_data", "importance": 0.4, "description": "FilterCoefficients for display" },
    { "id": "out", "label": "Audio Out", "type": "output", "importance": 1.0, "description": "Dry + allpass chain output (phaser-style notches)" }
  ],
  "edges": [
    { "from": "in", "to": "allpass", "type": "signal", "label": null },
    { "from": "freq", "to": "allpass", "type": "control", "label": null },
    { "from": "q", "to": "allpass", "type": "control", "label": "feedback" },
    { "from": "gain", "to": "allpass", "type": "control", "label": "ignored" },
    { "from": "mode", "to": "allpass", "type": "control", "label": "single mode" },
    { "from": "smoothing", "to": "allpass", "type": "control", "label": null },
    { "from": "enabled", "to": "allpass", "type": "control", "label": null },
    { "from": "allpass", "to": "coeffs", "type": "control", "label": "display update" },
    { "from": "allpass", "to": "out", "type": "signal", "label": null }
  ]
}
